{
  "id": "nuphar-luteum",
  "names": {
    "primary": "Nuphar Luteum",
    "latin": "Nuphar Luteum",
    "common": [
      "Yellow Pond-lily"
    ],
    "synonyms": [
      "NUPHAR LUTEUM"
    ]
  },
  "category": "homeopathic",
  "traditional": {
    "generalities": [
      {
        "text": "Main THE ENCYCLOPEDIA OF PURE MATERIA MEDICA By TIMOTHY F. ALLEN, A.M., M.D. Presented by Médi-T NUPHAR LUTEUM. Nuphar luteum, Smith. Natural order , Nymphæaceæ. Common names , Nixen-blume, Nenuphar Jaune. Preparation , Tincture of the root. Authorities. 1 , Dr. Pitet, Journ. de la Soc. Gal., 3, p. 129, proving with 4th dil., taken irregularly for several days; 2 , same, subsequent proving, frequent doses of 4th and 6th dils.; 3 , same, third proving with 6th, 7th, and 8th dils., continued for twelve days. (Symptoms in brackets are constitutional, that seem to have appeared as the effect of the drug in depressing the vitality). MIND. ► Excessive moral sensibility, giving one great pain on witnessing the sufferings of animals (eleventh day), [1] . HEAD. ► General Head. ► Heaviness in the whole head in the middle of the day (tenth day), [2] . ► Very painful bruising shaking in the brain at every step in walking (eleventh day), [2] . ► Dull pains in the anterior part of the base of the brain, on a level with the floor of the orbits (twentieth and following days), [3] . ► Dull or tearing pains, sometimes in the forehead, at others in the whole upper part of the head (tenth day), [2] . ► Forehead. ► Pressive headache in the forehead and left temple (ninth and tenth days); headache in the forehead, and by turns in the left temple, ceasing in the open air (eleventh day), [1] . ► Dull pains, sometimes lancinating, in the situation of the right anterior cerebral lobe (twenty-fifth day), [2] . ► Dull pains in the left anterior cerebral lobe (eleventh day), [2] . ► Dull, deep lancinations behind the left frontal eminence (tenth day), [2] . [10.] ► Boring pain, in transitory attacks, in the left anterior part of the forehead, in the evening (seventh day), [2] . ► Painful bruising shocks in the right anterior side of the brain when walking (twelfth day), [2] . ► Lancinations in the left anterior part of the brain (ninth and tenth days); similar, but less violent, sensations on the opposite side (tenth day), [3] . ► Temples. ► Painful pressure in the right temple (tenth day), [3] . ► Very painful feeling of weight in the temples, in the morning (twentieth and following days), [3] . ► Parietals. ► Acute lancinations in the left side of the brain (twelfth and following days), [3] . ► External Head. ► (Falling off of the hair), (twenty-seventh day), [2] . ► (Extremely violent itching of the whole scalp, particularly at night), (twenty-seventh day), [2] . EYE. ► Face pale, discolored eyes, though otherwise as well as usual (tenth day), [2] . ► Brow and Orbit. ► Painful heaviness in the orbit, at the base of the skull, a very frequent symptom since the beginning of the proving (twenty-fifth day), [2] . [20.] ► Dull pain, and sensation of painful weight in the orbit all day, since morning, in the right anterior cerebral lobe and right side of the occiput (twenty-third day), [2] . ► Dull pains occasionally beneath the orbital plate (eleventh day), [2] . ► Dull pains at the base of the orbit, forehead, and occiput, on the right side (twenty-fifth day), [3] . ► Vision. ► (When standing in the sun, a quantity of brilliant sparks filled the field of vision, converging from the circumference to the centre; frequently perceived subsequently, principally after hard coughing ), (twenty-third day), [2] . MOUTH. ► Sweetish taste several times a day; taste of Nuphar at the root of the tongue (fourth day), [2] . STOMACH. ► Slightly painful over the whole anterior surface of the stomach (nineteenth day), [2] . ► Weakness in the epigastric region, at times (twelfth day), [3] . ► Sensation of weakness and slight pain on pressing the epigastric region (nineteenth day), [2] . ABDOMEN. ► General Abdomen. ► Emission of flatulence, in the evening, with wind colic (seventeenth day), [2] . ► Some colic (sixth day), [1] . [30.] ► Dull deep colic pains, during the day, all around the waist (eighteenth day), [2] . RECTUM AND ANUS. ► Smarting and burning at the anus, after every stool (seventeenth day), [2] . ► Stitches, as if from needles, in the rectum, above the anus (twentieth and following days), [3] . STOOL. ► Diarrha. ► *Soft stools, preceded by some colic, for several days (eighth day), [2] . ► *Diarrhic stools, morning and evening, preceded by violent colic pains in the rectum, without having eaten more than ordinary (fifteenth day); diarrha, preceded by violent colic pains in the rectum, all night (sixteenth day); yellowish diarrha, two nights in succession, preceded by violent colic pains in the rectum; six stools from 8 P.M. to 6 A.M.; diarrhic stool during the day, after breakfast, and another after dinner; two during the evening (seventeenth day); two diarrhic stools, during the morning, preceded by colic pains in the rectum; two yellow diarrhic stools in the evening (eighteenth day); two yellow diarrhic stools between 4 and 5 A.M., and one during the day; diarrhic stool in the evening (nineteenth day); diarrhic stool, in the morning (twentieth day), [2] . ► *Yellow diarrha , especially very early in the morning, for three days past; five or six stools a day, without colic or epigastric trouble, except, at times, a sense of weakness in the epigastric region (twelfth day); the diarrha continues, notwithstanding a considerable diminution in the amount of food taken; the stools are always more numerous towards 5 or 6 A.M. (following days); soft diarrhic stool, preceded by colic, which disappeared after the stool (twenty-fifth day), [2] . URINARY ORGANS. ► Urine. ► The urine deposits a copious reddish sand, which is hard, and adheres to the vessel (seventeenth day), [2] . SEXUAL ORGANS. ► Male. ► Lancinations in the right testicle (nineteenth day), [2] . ► Dull transitory pain in the right testicle, for several days in succession; a similar pain at the extremity of the penis, on the right side; several lancinations in the left testicle, with pains at the extremity of the penis, on the left side (twenty-fifth day), [3] . ► Some pain in the right testicle (twentieth day), [2] . [40.] ► Diminution of erections and sexual appetite (twelfth and following days), [3] . ► *Complete absence of sexual desire; penis retracted; scrotum relaxed (eighth day), [2] . ► *Entire absence of erections and sexual desires; the voluptuous ideas which fill the imagination do not cause erection (tenth day), [2] . ► Continued absence of erections and sexual appetite (eighteenth day), [2] . ► *Diminution of lascivious thoughts and the sexual inclination, for some ten days ; opposite effects during the succeeding days, [1] . CHEST. ► Painful sensation behind the sternum, when running, as though the subjacent organs were violently shaken (ninth day), [2] . ► (Dull wandering pains in the left side of the chest), (twenty-seventh day), [2] . NECK AND BACK. ► Lumbar. ► Deep dull pain at the lowest part of the left lumbar region and in the posterior superior part of the external iliac fossa; it coincides with a similar, but not constant, pain in the internal iliac fossa of the same side (eighth day), [3] . ► Walking, even slowly, causes a painful stitch in the left flank, which is relieved by pressure (twelfth and following days), [3] . INFERIOR EXTREMITIES. ► Thigh. ► Frequent prickings on the posterior surface of the left thigh (sixth day), [1] . ► Leg. [50.] ► Constant restlessness and fatigue in the legs (tenth day), [2] . ► Painful drawings in the muscles of the anterior region of the left leg (tenth day), [2] . ► Toes. ► Lancinations in the plantar surface of the last phalanx of the right great toe, in the evening (eighth day), [2] . ► (Paroxysms of very acute, but transitory, pain in the inner border of the last joint of the right great toe, when walking), (twenty-third day), [2] . GENERAL SYMPTOMS. ► Weakness of the limbs, in the evening (twelfth and following days), [3] . ► Great impatience at the slightest contradiction (tenth day), [2] . ► Sense of weakness (nineteenth day), [2] . ► The strength, flesh, and healthy complexion, which had diminished, began to return (twenty-ninth and thirtieth days), [2] . SKIN. ► There appeared on different parts of the body a number of red blotches, tolerably regular in outline, ovoid or circular, prominent, and covered with little scales of a silvery white, in short, resembling psoriasis ; there were a few on the posterior surface of the arms, but they were most abundant on the anterior surface of the legs; they itched violently, especially in the evening; friction removed the little scales, which were rapidly reproduced, remained a few days, and then fell off again from the scratching induced by the itching; this eruption lasted a month and a half; as it disappeared, and the scales ceased to be reproduced, the skin at the place of each blotch became pale red or yellowish (after ten or twelve days), [1] . ► A red, slightly prominent patch, covered with little white scales, and itching violently, on the interior surface of the right arm, near the axilla (psoriasis), (twentieth and following days); a red, oval, prominent patch, as large as a five-cent piece (pièce de vingt-cinq centimes), on the internal surface of the left arm, exactly like a patch of psoriasis , covered with silvery scales, falling off and renewed again every few days, and itching violently, especially in the evening (twenty-fifth day), [3] . [60.] ► (Aggravation of a moderate pityriasis capitis of several years' standing; morning and evening, especially, the itching is intolerable, and the comb brings away a great quantity of hair), (twenty-third day), [2] . ► Sensations like fleabites, in different parts, for several days (eighth day), [3] . ► Sensation like fleabites, in different spots, on the legs, near the ankles, and on the arms near the wrist; a similar sensation on different parts of the skin of the body (twentieth and following days), [3] . CONDITIONS. ► Aggravation. ► ( Morning ), Weight in temples. ► ( Morning and evening ), Diarrha. ► ( Middle of day ), Head heavy. ► ( Evening ), Pain in forehead; emission of flatulence; weakness. ► ( Running ), Pain behind sternum. ► ( Stepping ), Shaking in brain. ► ( Walking ), Shocks in brain; stitch in left flank; pain in great toe. ► Amelioration. ► ( Open air ), Headache. ► ( Pressure ), Stitch in left flank. Copyright © Médi-T ® 2000 Main",
        "source_id": "allen-encyclopedia-1874"
      },
      {
        "text": "Clinical: Cholerine; Diarrhœa; Dyspepsia; Headache; Impotence; Psoriasis; Rhus poisoning; Seminal emissions; Typhoid-fever",
        "source_id": "clarke-dictionary-1900"
      },
      {
        "text": "Weakness and loss of power in limbs, evening. Lupus on arms. Prickings back of l. thigh. Constant restlessness and fatigue of legs. Lancinations in plantar surface of r. great toe.",
        "source_id": "clarke-dictionary-1900"
      },
      {
        "text": "General exhaustion ; weakness from loss of fluids. Every morning at 6 : stool liquid, yellow. Every night : colic and rumbling. For several years : virile function badly performed. Right : painful shocks in anterior brain. Left : dull pains in renal region. Painful shocks : in right anterior side of brain. Burning : at anus. Pricking pains : in rectum. Weakness : in limbs. Itching : of scrotum and perineum ; in different parts of body ; violent, on skin. TOUCH. PASSIVE MOTION. INJURIES. [45] [Nuph.]. Touch : renal region sensitive. Man, æt. 21, professor of literature ; suffering 8 days ; diarrhœa. Man, æt. 28, suffering three months ; diarrhœa. Man, æt. 33, jeweler, suffering a fortnight ; diarrhœa. Man, æt. 37, wood-carver, sick 3 months ; digestive troubles, weakness of sexual organs. Man, æt. 43, addicted to excesses of table and venery, has domestic trouble, has taken much old school and quack medicine, suffering 3 years ; entero-colitis. Miss B., æt. 54, suffering several weeks ; diarrhœa and psoriasis. Man, æt. 71, suffering a week ; cholerine. Man, suffering for nine years ; seminal emissions. Copyright © Médi-T ® 2002. Main.",
        "source_id": "hering-guiding-1879"
      }
    ],
    "male": [
      {
        "text": "Complete absence of sexual desire; parts relaxed; penis retracted. Impotency, with involuntary emissions during stool, when urinating. Spermatorrhœa. Pain in testicles and penis",
        "source_id": "boericke-1927"
      },
      {
        "text": "Entire absence of erections and desire; voluptuous ideas which fill imagination do not cause erections. Penis retracted, scrotum relaxed. Diminution of lascivious thoughts and desires for some days; opposite effect during succeeding days. Weakening nocturnal emissions while convalescing from typhoid. Involuntary losses during sleep, at stool, and when urinating, with complete absence of erections; inability to effect coitus; weakness; impaired digestion; pale, languid. Lancinations in r. testicle; in l. testicle; with pains at extremity of penis.",
        "source_id": "clarke-dictionary-1900"
      },
      {
        "text": "Entire absence of erections and sexual desire ; voluptuous ideas which fill imagination do not cause erections. Complete absence of sexual desire ; penis retracted ; scrotum relaxed. Weakening nocturnal emissions while convalescing from typhoid. Involuntary seminal losses during sleep, at stool, and when urinating, with complete absence of erections ; inability to perform generative act ; general weakness ; digestion impaired ; pale and languid.",
        "source_id": "hering-guiding-1879"
      }
    ],
    "stool_rectum": [
      {
        "text": "Entero-colitis. Yellow diarrhœa; worse in the morning. Diarrhœa during typhoid",
        "source_id": "boericke-1927"
      },
      {
        "text": "Smarting and burning at anus after every stool. Stitches as from needles in rectum, above anus. Soft stools preceded by some colic for several days; or painless diarrhœa. Yellow diarrhœa, esp. very early in morning (4 to 6 a.m.). Stools: liquid, yellow, fetid. Much exhaustion with stools; sense of exhaustion in epigastric region.",
        "source_id": "clarke-dictionary-1900"
      },
      {
        "text": "Stools : liquid, yellow, fetid. Diarrhœa, obliging him to get up several times towards 5 or 6 A. M. ; burning at anus ; general depression ; no colic. Early morning stool, weakness of limbs, general exhaustion. Morning diarrhœa with colic ; between 4 and 6 A. M., two or three stools and generally one in evening. Stool liquid, light yellow ; call urgent, every morning at six, followed by two or three more passages in a few hours and no more till next morning. θ Diarrhœa. Soft stools preceded by colic. Diarrhœa : painless in morning ; with exhaustion ; during typhoid. Entero-colitis, with severe colicky pains in rectum and characteristic stools ; psoriasis, on different parts of body, with great itching. Cholerine since a week ; stools cause great exhaustion, patient being in last stage of marasmus. Pricking pains in rectum as from needles.",
        "source_id": "hering-guiding-1879"
      }
    ],
    "dosing": {
      "notes": "Tincture to sixth potency"
    },
    "keynotes": [
      {
        "text": "color=\"#800000\">NUPHAR LUTEUM Yellow Pond-lily Produces nervous weakness, with marked symptoms in the sexual sphere.",
        "source_id": "boericke-1927"
      },
      {
        "text": "Nuphar l., the Yellow Pond Lily, was proved by Pitet, and many of his symptoms have been clinically confirmed. Most marked was a yellow diarrhœa coming on in the early hours of the morning. With the diarrhœa is great exhaustion. Nuph. has cured many cases of diarrhœa so characterised, and even cases of typhoid fever. Another marked feature of the proving was the excessive depression of the male generative system; and Nuph. has done good work in analogous conditions, and headaches associated therewith. The diarrhœa was 4 to 6 a.m.; after the least excess of any kind. Weakness and itching were evening. Walking = painful shocks in hams; and pain in flank, which was > by pressure. Day after coitus.",
        "source_id": "clarke-dictionary-1900"
      },
      {
        "text": "A Text-Book of Materia Medica. (Characteristic, Analytical, and Comparative.) By Pr. Allen Corson Cowperthwaite, M. D., PH. D., LL. D. NUPHAR LUTEUM. (Nenuphar luteum. ) Common name.- European Pond Lily. General Analysis.- Acts most prominently upon the lower portion of the intestinal canal and upon the male generative organs. Characteristic symptoms. Head.- (Nuphar luteum) Pressive headache in forehead and temples, ceasing in the open air. Dull, deep, lancinating pains behind the left frontal eminence. Painful, bruising shocks in the brain at every step. Eyes.- (Nuphar luteum) Dull pain and sensation of weight in orbit. Brilliant sparks before the eyes, especially after hard coughing. Stool.- (Nuphar luteum) Soft stools, preceded by colic ; more mornings. Yellow diarrhoea in the morning. Smarting and burning in anus after stool. ( Ars., Sulph .) Stitches, as from needles, in rectum. Painless morning diarrhoea. (Podo.) Urinary Organs.- (Nuphar luteum) Urine deposits a copious reddish sand (Cinch., Natr. mur., Lyc., Phos.), which adheres to vessel. Male Organs.- (Nuphar luteum) Complete absence of sexual desire (Agn.) ; voluptuous thoughts do not cause erection (Agar., Agn ., Coni.) ; penis retracted ; scrotum relaxed. Severe lancinations in both testicles, with pains in end of penis. Impotency, with involuntary emissions (Agar., Agn., Coni., Phos., Phos. ac.) ; during sleep, at stool, and when urinating. Skin.- (Nuphar luteum) Sensation like flea bites in different spots. Itching eruption, resembling psoriasis. Therapeutic Range.- (Nuphar luteum) Morning diarrhoea ; entero-colitis, chronic ; sexual debility ; impotence ; spermatorrhoea. Compare.- (Nuphar luteum) Ars., Agn., Baryt. c., Coni., Gels., Podo., Rumex, Sulph. Copyright © Robert Séror 2003",
        "source_id": "cowperthwaite-textbook-1891"
      }
    ],
    "relationships": {
      "_raw": [
        "Compare: Early morning diarrhœa, Sul., Nat. sul., Rumex, Pod. Sexual debility, Gels., Con., Dig., Nat. m., Chi."
      ]
    },
    "mental_emotional": [
      {
        "text": "Impatient of slightest contradiction. Excessive moral sensibility, acute pain on witnessing sufferings of animals.",
        "source_id": "clarke-dictionary-1900"
      },
      {
        "text": "Impatience at slightest contradiction. Excessive sensibility giving one pain in witnessing sufferings of animals.",
        "source_id": "hering-guiding-1879"
      }
    ],
    "head": [
      {
        "text": "Heaviness of head. Bruised shaking in brain. Dull pains in front part of base of brain on level of orbits. Bruised, painful shocks, r. anterior side of brain on walking. Lancination in r. and l. anterior lobes of brain. Headaches attending depressed states of generative organs. (Pityriasis capitis very much aggravated, with much itching and falling out of the hair).",
        "source_id": "clarke-dictionary-1900"
      },
      {
        "text": "Painful bruised shocks in right anterior side of brain, in walking. Headaches attending depressed conditions of generative organs.",
        "source_id": "hering-guiding-1879"
      }
    ],
    "eyes": [
      {
        "text": "When standing in sun brilliant sparks filled field of vision, converging from circumference to centre (an old symptom revived, and subsequently reproduced frequently, esp. after hard coughing).",
        "source_id": "clarke-dictionary-1900"
      },
      {
        "text": "When standing in sun brilliant sparks filled field of vision, converging from circumference to centre.",
        "source_id": "hering-guiding-1879"
      }
    ],
    "mouth_throat": [
      {
        "text": "Sweetish taste. Tongue white; mouth pasty.",
        "source_id": "clarke-dictionary-1900"
      },
      {
        "text": "Sweetish taste in mouth.",
        "source_id": "hering-guiding-1879"
      }
    ],
    "stomach_abdomen": [
      {
        "text": "Painful sensation of weariness in stomach; digestion slow; wind colic, early morning, with liquid, sour-smelling stools; with sexual weakness and pollutions; after coitus. Exhaustion in epigastrium. Colicky pains all round waist; 5 to 7 a.m.",
        "source_id": "clarke-dictionary-1900"
      },
      {
        "text": "Tongue white ; mouth pasty ; painful sensation of weariness in stomach ; digestion slow ; wind colic, principally early in morning, with liquid or sour-smelling stools ; for several years virile function had been badly performed ; frequent pollutions during sleep ; constant itching of scrotum and perineum ; small desire for coitus ; infrequent and feeble erections ; general weariness ; < on day succeeding sexual connection. Appetite good, at times excessive ; frequent regurgitation of an acrid and corrosive taste ; digestion slow ; colic and rumbling every night and waked several times from 5 to 7 A. M. to go to stool, which was liquid or soft, yellowish, and either sourish or fetid ; < from least excess of any kind ; sleep agitated ; heat in palms ; frequent pulse ; at times dull pains in left renal region, which was sensitive to touch. θ Entero-colitis.",
        "source_id": "hering-guiding-1879"
      }
    ],
    "urinary": [
      {
        "text": "Urine deposits copious reddish sand, which is hard and adheres to the vessel.",
        "source_id": "clarke-dictionary-1900"
      }
    ],
    "chest_heart": [
      {
        "text": "Pain behind sternum, when running, as though subjacent organs violently shaken.",
        "source_id": "clarke-dictionary-1900"
      }
    ],
    "back": [
      {
        "text": "Dull pain in l. lower lumbar region. When walking painful stitch to flank, > by pressure. Sensitive on renal region.",
        "source_id": "clarke-dictionary-1900"
      }
    ],
    "skin": [
      {
        "text": "Violent itching. On different parts of body red blotches, tolerably regular in outline, ovoid or circular, prominent and covered with little silvery white scales; violent itching, evening; as eruption disappeared, scales ceased to be reproduced, and skin at place of each blotch became pale red or yellowish. (Rhus tox poisoning; relieved pain and swelling and hastened recovery. .). Psoriasis; pityriasis capitis. Copyright © Médi-T ® 2000 Main.",
        "source_id": "clarke-dictionary-1900"
      },
      {
        "text": "Violent itching. On different parts of body red blotches, tolerably regular in outline, ovoid or circular, prominent and covered with little silvery white scales ; violent itching, < in evening ; as eruption disappeared scales ceased to be reproduced, and skin at place of each blotch became pale red or yellowish. Rhus tox poisoning ; relieved pain and swelling and hastened recovery. Psoriasis ; pityriasis capitis.",
        "source_id": "hering-guiding-1879"
      }
    ],
    "extremities": [
      {
        "text": "Leprous eruption on arm. Sensation of weakness and loss of power in limbs ; < in evening.",
        "source_id": "hering-guiding-1879"
      }
    ],
    "modalities": [
      {
        "text": "REST. POSITION. MOTION. [35] [Nuph.]. Walking : painful shocks in brain. Between 4 and 6 A. M. : two or three stools. From 5 to 7 A. M. : wakes several times to go to stool. Morning : wind colic ; stool and colic ; painless diarrhœa. Evening : one stool ; weakness in limbs < ; itching <.",
        "source_id": "hering-guiding-1879"
      }
    ]
  },
  "evidence": {},
  "provenance": {
    "sources": [
      "allen-encyclopedia-1874",
      "boericke-1927",
      "clarke-dictionary-1900",
      "cowperthwaite-textbook-1891",
      "hering-guiding-1879"
    ]
  }
}